volutemcp/__init__.py
volutemcp/__main__.py
volutemcp/config.py
volutemcp/powerpoint_metadata.py
volutemcp/powerpoint_tools.py
volutemcp/sdk.py
volutemcp/server.py
volutemcp/server_local.py
volutemcp/slide_capture_tools.py
volutemcp-1.1.1.dist-info/METADATA
volutemcp-1.1.1.dist-info/WHEEL
volutemcp-1.1.1.dist-info/entry_points.txt
volutemcp-1.1.1.dist-info/top_level.txt
volutemcp-1.1.1.dist-info/RECORD
