Metadata-Version: 2.4
Name: volutemcp
Version: 1.1.1
Summary: MCP server for PowerPoint analysis and multimodal AI integration - comprehensive metadata extraction and slide image capture for agents
Home-page: https://gitlab.com/coritan/volutemcp
Author: Coritan
Author-email: Coritan <your-email@example.com>
License: MIT
Project-URL: Homepage, https://gitlab.com/coritan/volutemcp
Project-URL: Repository, https://gitlab.com/coritan/volutemcp.git
Project-URL: Issues, https://gitlab.com/coritan/volutemcp/-/issues
Project-URL: Documentation, https://gitlab.com/coritan/volutemcp/-/blob/main/DEVELOPER_GUIDE.md
Keywords: mcp,powerpoint,ai,agents,desktop,automation,com,multimodal,vision,slides,image-capture
Classifier: Development Status :: 4 - Beta
Classifier: Intended Audience :: Developers
Classifier: License :: OSI Approved :: MIT License
Classifier: Operating System :: Microsoft :: Windows
Classifier: Programming Language :: Python :: 3
Classifier: Programming Language :: Python :: 3.8
Classifier: Programming Language :: Python :: 3.9
Classifier: Programming Language :: Python :: 3.10
Classifier: Programming Language :: Python :: 3.11
Classifier: Topic :: Software Development :: Libraries :: Python Modules
Classifier: Topic :: Office/Business :: Office Suites
Classifier: Topic :: Scientific/Engineering :: Artificial Intelligence
Requires-Python: >=3.8
Requires-Dist: fastmcp>=2.0.0
Requires-Dist: httpx>=0.25.0
Requires-Dist: python-dotenv>=1.0.0
Requires-Dist: pydantic>=2.0.0
Requires-Dist: python-pptx>=0.6.21
Requires-Dist: Pillow>=9.0.0
Requires-Dist: pywin32>=306; platform_system == "Windows"
Provides-Extra: dev
Requires-Dist: pytest>=7.0.0; extra == "dev"
Requires-Dist: pytest-asyncio>=0.21.0; extra == "dev"
Requires-Dist: build>=0.10.0; extra == "dev"
Requires-Dist: twine>=4.0.0; extra == "dev"
Dynamic: author
Dynamic: home-page
Dynamic: requires-python
